MANIFEST.in
README.md
setup.cfg
setup.py
pdfannot/__init__.py
pdfannot/annot_utils.py
pdfannot/extractannot.py
pdfannot/genannot.py
pdfannot.egg-info/PKG-INFO
pdfannot.egg-info/SOURCES.txt
pdfannot.egg-info/dependency_links.txt
pdfannot.egg-info/requires.txt
pdfannot.egg-info/top_level.txt
pdfannot/test_ressources/pdf_without_annot.pdf
ressources/facture_for_testing_word_order.pdf
ressources/pdf_annot_3_output.xlsx
ressources/pdf_test_annot.pdf
ressources/pdf_test_annot.pdf-marked
ressources/pdf_test_annot_2.pdf
ressources/pdf_test_annot_2.pdf-marked
ressources/pdf_test_annot_2_output.xlsx
ressources/pdf_test_annot_3.pdf
ressources/pdf_test_annot_3.pdf-marked
ressources/pdf_test_annot_output.xlsx
ressources/pdf_with_no_annotations.pdf
ressources/pdf_without_annot.pdf