Metadata-Version: 2.1
Name: pdfannot
Version: 2019.6.5.1
Summary: PDF Annotation Utils
Home-page: https://bitbucket.org/ArthurRenaud/pdfannot/
Author: Arthur RENAUD ; Antoine MARULLAZ => Stackadoc
Author-email: arthur.b.renaud@gmail.com
License: UNKNOWN
Platform: UNKNOWN
Classifier: Programming Language :: Python
Classifier: Development Status :: 1 - Planning
Classifier: License :: OSI Approved
Classifier: Natural Language :: French
Classifier: Operating System :: OS Independent
Classifier: Programming Language :: Python :: 3.6
Classifier: Topic :: Communications
Requires-Python: >=3.5
